CHANGELOG.rst
MANIFEST.in
README.rst
setup.py
tabletext.py
tabletext.egg-info/PKG-INFO
tabletext.egg-info/SOURCES.txt
tabletext.egg-info/dependency_links.txt
tabletext.egg-info/entry_points.txt
tabletext.egg-info/top_level.txt