Metadata-Version: 1.0
Name: tabletext
Version: 0.1
Summary: Python library and command line utility to pretty-print      tabular data
Home-page: https://github.com/Thibauth/tabletext
Author: Thibaut Horel
Author-email: thibaut.horel+tabletext@gmail.com
License: GNU GPLv3
Platform: UNKNOWN
